akihiro/__init__.py
akihiro/core.py
akihiro/key.py
akihiro-1.6.0.dist-info/LICENSE
akihiro-1.6.0.dist-info/METADATA
akihiro-1.6.0.dist-info/WHEEL
akihiro-1.6.0.dist-info/top_level.txt
akihiro-1.6.0.dist-info/RECORD
