Metadata-Version: 2.1
Name: akihiro
Version: 1.6.0
Summary: Python package to enhance programming experience with AI LLM capabilities
Home-page: https://github.com/Akihiro2004/akihiro
Author: Darrien Rafael Wijaya
Author-email: darrienwijaya@gmail.com
Classifier: Development Status :: 4 - Beta
Classifier: Intended Audience :: Developers
Classifier: Programming Language :: Python :: 3
Classifier: License :: OSI Approved :: MIT License
Classifier: Operating System :: OS Independent
Classifier: Topic :: Software Development :: Libraries :: Python Modules
Classifier: Topic :: Utilities
Requires-Python: >=3.6
License-File: LICENSE
Requires-Dist: requests
Requires-Dist: faker
Requires-Dist: sumy
Requires-Dist: googletrans
